<?xml version='1.0'?>
<!DOCTYPE platform SYSTEM "https://simgrid.org/simgrid.dtd">
<!-- Platform generated by ENIGMA Platform Generator -->
<platform version="4.1">
  <zone id="hybrid_platform" routing="Full">
    <prop id="mobility_dir" value="platforms/coords/"/>
    <zone id="edge_cluster_0_zone" routing="Cluster">
      <cluster bb_bw="1GBps" bb_lat="10us" bw="125MBps" core="1" id="edge_cluster_0" lat="50us" prefix="edge_cluster_0_node_" radical="0-2" router_id="edge_cluster_0_router" speed="1Gf" suffix=""/>
    </zone>
    <zone id="edge_cluster_1_zone" routing="Cluster">
      <cluster bb_bw="1GBps" bb_lat="10us" bw="125MBps" core="1" id="edge_cluster_1" lat="50us" prefix="edge_cluster_1_node_" radical="0-2" router_id="edge_cluster_1_router" speed="1Gf" suffix=""/>
    </zone>
    <zone id="fog_cluster_0_zone" routing="Cluster">
      <cluster bb_bw="1GBps" bb_lat="10us" bw="1GBps" core="4" id="fog_cluster_0" lat="10us" prefix="fog_cluster_0_node_" radical="0-0" router_id="fog_cluster_0_router" speed="10Gf" suffix=""/>
    </zone>
    <zone id="cloud_cluster_0_zone" routing="Cluster">
      <cluster bb_bw="1GBps" bb_lat="10us" bw="10GBps" core="16" id="cloud_cluster_0" lat="1us" prefix="cloud_cluster_0_node_" radical="0-3" router_id="cloud_cluster_0_router" speed="100Gf" suffix=""/>
    </zone>
    <link bandwidth="500MBps" id="link_edge_cluster_0_to_fog_cluster_0" latency="10ms"/>
    <link bandwidth="500MBps" id="link_edge_cluster_1_to_fog_cluster_0" latency="10ms"/>
    <link bandwidth="5GBps" id="link_fog_cluster_0_to_cloud_cluster_0" latency="50ms"/>
    <link bandwidth="2GBps" id="link_edge_cluster_0_to_cloud_cluster_0" latency="30ms"/>
    <link bandwidth="2GBps" id="link_edge_cluster_1_to_cloud_cluster_0" latency="30ms"/>
    <zoneRoute dst="fog_cluster_0_zone" gw_dst="fog_cluster_0_router" gw_src="edge_cluster_0_router" src="edge_cluster_0_zone">
      <link_ctn id="link_edge_cluster_0_to_fog_cluster_0"/>
    </zoneRoute>
    <zoneRoute dst="fog_cluster_0_zone" gw_dst="fog_cluster_0_router" gw_src="edge_cluster_1_router" src="edge_cluster_1_zone">
      <link_ctn id="link_edge_cluster_1_to_fog_cluster_0"/>
    </zoneRoute>
    <zoneRoute dst="cloud_cluster_0_zone" gw_dst="cloud_cluster_0_router" gw_src="fog_cluster_0_router" src="fog_cluster_0_zone">
      <link_ctn id="link_fog_cluster_0_to_cloud_cluster_0"/>
    </zoneRoute>
    <zoneRoute dst="cloud_cluster_0_zone" gw_dst="cloud_cluster_0_router" gw_src="edge_cluster_0_router" src="edge_cluster_0_zone">
      <link_ctn id="link_edge_cluster_0_to_cloud_cluster_0"/>
    </zoneRoute>
    <zoneRoute dst="cloud_cluster_0_zone" gw_dst="cloud_cluster_0_router" gw_src="edge_cluster_1_router" src="edge_cluster_1_zone">
      <link_ctn id="link_edge_cluster_1_to_cloud_cluster_0"/>
    </zoneRoute>
  </zone>
</platform>
